pokerengine/__init__.py
pokerengine/card.py
pokerengine/constants.py
pokerengine/engine.py
pokerengine/enums.py
pokerengine/enums_schema/__init__.py
pokerengine/enums_schema/action.py
pokerengine/enums_schema/combination.py
pokerengine/enums_schema/position.py
pokerengine/enums_schema/rank.py
pokerengine/enums_schema/round.py
pokerengine/enums_schema/state.py
pokerengine/enums_schema/suit.py
pokerengine/evaluation.py
pokerengine/exceptions.py
pokerengine/pokerengine.py
pokerengine/pokerengine_core/__init__.pyi
pokerengine/pokerengine_core/card.pyi
pokerengine/pokerengine_core/constants.pyi
pokerengine/pokerengine_core/engine.pyi
pokerengine/pokerengine_core/enums/__init__.pyi
pokerengine/pokerengine_core/enums/action.pyi
pokerengine/pokerengine_core/enums/combination.pyi
pokerengine/pokerengine_core/enums/position.pyi
pokerengine/pokerengine_core/enums/rank.pyi
pokerengine/pokerengine_core/enums/round.pyi
pokerengine/pokerengine_core/enums/state.pyi
pokerengine/pokerengine_core/enums/suit.pyi
pokerengine/pokerengine_core/evaluation.pyi
pokerengine/pokerengine_core/exceptions.pyi
pokerengine/pokerengine_core/pokerengine.pyi
pokerengine/pokerengine_core.cpython-313-x86_64-linux-gnu.so
pokerengine/pretty_string.py
pokerengine/schema.py
pokerengine-1.9.7.dist-info/METADATA
pokerengine-1.9.7.dist-info/WHEEL
pokerengine-1.9.7.dist-info/entry_points.txt
pokerengine-1.9.7.dist-info/licenses/LICENSE
pokerengine-1.9.7.dist-info/RECORD
