Metadata-Version: 2.1
Name: pokerengine
Version: 1.9.7
Summary: Poker Library
Keywords: pokerlost,engine,poker,texas,holdem,texas-holdem,texas_holdem,pybind11,scikit-build-core,fast,c++,magic_enum,stubs,python-stubs,python_stubs,pythonstubs,py-stubs,py_stubs,pystubs
Author: pokerlost
Requires-Python: >=3.8
Requires-Dist: pydantic~=2.11.2
Provides-Extra: dev
Requires-Dist: black~=23.10.0; extra == "dev"
Requires-Dist: isort~=5.12.0; extra == "dev"
Requires-Dist: ruff~=0.1.1; extra == "dev"
Requires-Dist: pre-commit~=3.5.0; extra == "dev"
Provides-Extra: build
Requires-Dist: build~=1.2.1; extra == "build"
Requires-Dist: twine~=5.0.0; extra == "build"
License-File: LICENSE
